[{"ID":1.0,"FridgeIndex":1.0,"CheckItem":1.0,"Target":64.0,"Money":100.0,"Recycle":5.0,"RecycleAdd":5.0},{"ID":2.0,"FridgeIndex":1.0,"CheckItem":2.0,"Target":53.0,"Money":100.0,"Recycle":5.0,"RecycleAdd":5.0},{"ID":3.0,"FridgeIndex":2.0,"CheckItem":3.0,"Target":40.0,"Money":100.0,"Recycle":5.0,"RecycleAdd":5.0},{"ID":4.0,"FridgeIndex":2.0,"CheckItem":4.0,"Target":48.0,"Money":100.0,"Recycle":5.0,"RecycleAdd":5.0},{"ID":5.0,"FridgeIndex":2.0,"CheckItem":5.0,"Target":40.0,"Money":100.0,"Recycle":5.0,"RecycleAdd":5.0},{"ID":6.0,"FridgeIndex":1.0,"CheckItem":6.0,"Target":64.0,"Money":100.0,"Recycle":5.0,"RecycleAdd":5.0},{"ID":7.0,"FridgeIndex":1.0,"CheckItem":7.0,"Target":53.0,"Money":100.0,"Recycle":5.0,"RecycleAdd":5.0},{"ID":8.0,"FridgeIndex":2.0,"CheckItem":8.0,"Target":40.0,"Money":100.0,"Recycle":5.0,"RecycleAdd":5.0},{"ID":9.0,"FridgeIndex":2.0,"CheckItem":9.0,"Target":56.0,"Money":100.0,"Recycle":5.0,"RecycleAdd":5.0},{"ID":10.0,"FridgeIndex":2.0,"CheckItem":10.0,"Target":46.0,"Money":100.0,"Recycle":5.0,"RecycleAdd":5.0}]